thx/__init__.py
thx/__main__.py
thx/__version__.py
thx/cli.py
thx/config.py
thx/context.py
thx/core.py
thx/main.py
thx/py.typed
thx/runner.py
thx/types.py
thx/utils.py
thx/tests/__init__.py
thx/tests/__main__.py
thx/tests/cli.py
thx/tests/config.py
thx/tests/context.py
thx/tests/helper.py
thx/tests/runner.py
thx/tests/types.py
thx/tests/utils.py
thx-0.7.0.dist-info/entry_points.txt
thx-0.7.0.dist-info/LICENSE
thx-0.7.0.dist-info/WHEEL
thx-0.7.0.dist-info/METADATA
thx-0.7.0.dist-info/RECORD
