Metadata-Version: 2.3
Name: thx
Version: 0.7.0
Summary: Fast command runner for Python projects.
Author-email: Amethyst Reese <amethyst@n7.gg>
Requires-Python: >=3.8
Classifier: Intended Audience :: Developers
Classifier: License :: OSI Approved :: MIT License
Classifier: Topic :: Utilities
Classifier: Typing :: Typed
Requires-Dist: aioitertools >= 0.10.0b1
Requires-Dist: click >= 8.0
Requires-Dist: packaging >= 21.0
Requires-Dist: rich >= 11.0.0
Requires-Dist: tomli >= 1.0
Requires-Dist: trailrunner >= 1.1
Requires-Dist: typing_extensions >= 4.0
Requires-Dist: watchdog >= 2.1
Requires-Dist: aioitertools==v0.11.0 ; extra == "dev"
Requires-Dist: click==8.1.7 ; extra == "dev"
Requires-Dist: packaging==24.0 ; extra == "dev"
Requires-Dist: rich==13.7.1 ; extra == "dev"
Requires-Dist: tomli==2.0.1 ; extra == "dev"
Requires-Dist: trailrunner==1.4.0 ; extra == "dev"
Requires-Dist: typing_extensions == 4.12.0 ; extra == "dev"
Requires-Dist: watchdog==4.0.1 ; extra == "dev"
Requires-Dist: attribution==1.7.1 ; extra == "dev"
Requires-Dist: black==24.4.2 ; extra == "dev"
Requires-Dist: build>=1.2 ; extra == "dev"
Requires-Dist: coverage==7.5.3 ; extra == "dev"
Requires-Dist: flit==3.9.0 ; extra == "dev"
Requires-Dist: flake8==7.0.0 ; extra == "dev"
Requires-Dist: mypy==1.10.0 ; extra == "dev"
Requires-Dist: ufmt==2.6.0 ; extra == "dev"
Requires-Dist: usort==1.0.8.post1 ; extra == "dev"
Requires-Dist: sphinx==7.3.7 ; extra == "docs" and ( python_version > '3.8')
Requires-Dist: sphinx-mdinclude==0.6.1 ; extra == "docs"
Project-URL: Documentation, https://thx.omnilib.dev
Project-URL: Github, https://github.com/omnilib/thx
Provides-Extra: dev
Provides-Extra: docs
